{
    "reporter": "@zebrunner/javascript-agent-cypress",
    "reporterOptions": {
        "reportingServerHostname": "https://mycompany.zebrunner.com/",
        "reportingServerAccessToken": "someaccesskey",
        "reportingProjectKey": "DEF",
        "reportingRunDisplayName": "Cypress Demo",
        "reportingRunLocale": "en_US",
        "reportingSlackChannels": "dev",
        "reportingEmailRecipients": "asukhodolova@solvd.com",
        "tcm": {
            "testCaseStatus": {
              "onPass": "",
              "onFail": ""
            },
            "zebrunner": {
              "pushResults": true,
              "pushInRealTime": true,
              "testRunId": 19
            }
        }
    }
}